modeldb/__init__.py
modeldb/commands.py
modeldb/config.py
modeldb/data.py
modeldb/hocscripts.py
modeldb/modeldb-run.yaml
modeldb/modeldb.py
modeldb/modelrun.py
modeldb/progressbar.py
modeldb/report.py
modeldb/showgout.hoc
modeldb/templates/diffreport.html
modeldb/templates/report.html
modeldb/templates/runtimes.html
nrn_modeldb_ci-0.3.0.dist-info/LICENSE.txt
nrn_modeldb_ci-0.3.0.dist-info/METADATA
nrn_modeldb_ci-0.3.0.dist-info/WHEEL
nrn_modeldb_ci-0.3.0.dist-info/entry_points.txt
nrn_modeldb_ci-0.3.0.dist-info/top_level.txt
nrn_modeldb_ci-0.3.0.dist-info/RECORD
