Metadata-Version: 2.1
Name: nrn-modeldb-ci
Version: 0.3.0
Summary: NEURON ModelDB CI tools
Home-page: https://github.com/neuronsimulator/nrn-modeldb-ci
Author: EPFL Blue Brain Project & Yale
Author-email: alexandru.savulescu@epfl.ch
License: BSD-3-Clause
License-File: LICENSE.txt
Requires-Dist: requests
Requires-Dist: pyyaml
Requires-Dist: docopt
Requires-Dist: jinja2
Requires-Dist: pyvirtualdisplay
Requires-Dist: pyqt5
Requires-Dist: ipython
Requires-Dist: matplotlib
Requires-Dist: scipy
Requires-Dist: 2to3
